TfELM/tfelm.py
TfELM/Layers/ELMLayer.py
TfELM/Layers/GELM_AE_Layer.py
TfELM/Layers/KELMLayer.py
TfELM/Layers/OSELMLayer.py
TfELM/Layers/SSELMLayer.py
TfELM/Layers/SSKELMLayer.py
TfELM/Layers/SubELMLayer.py
TfELM/Layers/USELMLayer.py
TfELM/Layers/USKELMLayer.py
TfELM/Layers/WELMLayer.py
TfELM/Models/DeepELMModel.py
TfELM/Models/DrELMModel.py
TfELM/Models/EHDrELMModel.py
TfELM/Models/ELMModel.py
TfELM/Models/KELMModel.py
TfELM/Models/LRFELMModel.py
TfELM/Models/MELMModel.py
TfELM/Models/ML_ELMModel.py
TfELM/Models/OSELMModel.py
TfELM/Models/RCELMModel.py
TfELM/Models/SSELMModel.py
TfELM/Models/SSKELMModel.py
TfELM/Models/USELMModel.py
TfELM/Models/USKELMModel.py
TfELM/Optimizers/ELMMAOptimizer.py
TfELM/Optimizers/ELMOptimizer.py
TfELM/Optimizers/FISTAELMOptimizer.py
TfELM/Optimizers/ISTAELMOptimizer.py
TfELM/Optimizers/LBFGSELMOptimizer.py
TfELM/Optimizers/PGDELMOptimizer.py
TfELM/Resources/ActivationFunction.py
TfELM/Resources/FastPinv.py
TfELM/Resources/Kernel.py
TfELM/Resources/ReceptiveFieldGaussianGenerator.py
TfELM/Resources/ReceptiveFieldGenerator.py
TfELM/Resources/SSRepeatedKFold.py
TfELM/Resources/apply_denoising.py
TfELM/Resources/generate_contrainted_weights.py
TfELM/Resources/generate_random_filters.py
TfELM/Resources/get_layers.py
TfELM/Resources/gram_schmidt.py
TfELM/Resources/kernel_distances.py
TfELM/Resources/labelize_images.py
TfELM/Resources/os_elm_resources.py
TfELM/Resources/proximal_operator.py
TfELM/Resources/rmse.py
TfELM/Resources/sqrt_pooling.py
TfELM/Resources/ss_cross_val_score.py
TfELM/Resources/ss_split_dataset.py
TfELM-1.1.dist-info/LICENSE.md
TfELM-1.1.dist-info/METADATA
TfELM-1.1.dist-info/WHEEL
TfELM-1.1.dist-info/top_level.txt
TfELM-1.1.dist-info/RECORD
