Metadata-Version: 2.1
Name: TfELM
Version: 1.1
Summary: This framework provides a comprehensive set of tools and utilities for implementing and experimenting with Extreme Learning Machines using Python and TensorFlow. ELMs are a type of machine learning algorithm known for their simplicity, efficiency, and scalability, making them ideal for various applications, including classification, regression, and feature learning tasks.
Author-email: Karol Struniawski <struniawski.karol@gmail.com>
Maintainer-email: Karol Struniawski <struniawski.karol@gmail.com>
License: Creative Commons Legal Code
Project-URL: Documentation, https://kstruniawski.github.io/TfELM
Project-URL: Repository, https://github.com/KStruniawski/TfELM
Keywords: Extreme Learning Machine,TensorFlow,Python,Neural networks,Artificial intelligence,Machine learning
Classifier: Development Status :: 5 - Production/Stable
Classifier: Programming Language :: Python :: 3
Requires-Python: >=3.8
License-File: LICENSE.md
Requires-Dist: tensorflow >=2.10.0
Requires-Dist: keras >=2.10.0
Requires-Dist: numpy >=1.24.0
Requires-Dist: h5py >=3.7.0
Requires-Dist: scikit-learn >=1.2.0
Requires-Dist: tqdm >=4.66.0
Requires-Dist: mealpy ==2.5.3
Requires-Dist: pandas
